qpax/__init__.py
qpax/diff_qp.py
qpax/elastic_qp.py
qpax/pdip.py
qpax/pdip_relaxed.py
qpax-0.0.9.dist-info/LICENSE
qpax-0.0.9.dist-info/METADATA
qpax-0.0.9.dist-info/WHEEL
qpax-0.0.9.dist-info/top_level.txt
qpax-0.0.9.dist-info/RECORD
