Metadata-Version: 2.1
Name: qpax
Version: 0.0.9
Summary: Differentiable QP solver in JAX.
Author-email: Kevin Tracy <ktracy@cmu.edu>
License: MIT
Project-URL: Homepage, https://github.com/kevin-tracy/qpax
Keywords: optimization,automatic differentiation,jax
Classifier: Intended Audience :: Science/Research
Classifier: Topic :: Scientific/Engineering :: Artificial Intelligence
Classifier: License :: OSI Approved :: MIT License
Classifier: Programming Language :: Python :: 3
Classifier: Programming Language :: Python :: 3.7
Classifier: Programming Language :: Python :: 3.8
Classifier: Programming Language :: Python :: 3.9
Requires-Python: >=3.7
License-File: LICENSE
Requires-Dist: jax>=0.4.0
Requires-Dist: jaxlib>=0.4.0
Provides-Extra: dev
Requires-Dist: pre-commit; extra == "dev"
Requires-Dist: pytest; extra == "dev"
